app/__init__.py
app/admin.py
app/config.py
app/functions.py
app/hcx_helper.py
app/models.py
app/tests.py
app/urls.py
app/views.py
app/migrations/0001_initial.py
app/migrations/__init__.py
authentication/__init__.py
authentication/admin.py
authentication/config.py
authentication/forms.py
authentication/models.py
authentication/tests.py
authentication/urls.py
authentication/views.py
authentication/migrations/__init__.py
core/__init__.py
core/asgi.py
core/settings.py
core/urls.py
core/wsgi.py
HCX_Migration-0.0.1.dist-info/METADATA
HCX_Migration-0.0.1.dist-info/WHEEL
HCX_Migration-0.0.1.dist-info/top_level.txt
HCX_Migration-0.0.1.dist-info/RECORD
