Metadata-Version: 2.1
Name: HCX-Migration
Version: 0.0.1
Summary: HCX Migration Project
Home-page: 
Author: Mohammed Amir Khan
Author-email: <mohammedamir.k@hcl.com>
License: UNKNOWN
Platform: UNKNOWN
Classifier: Programming Language :: Python :: 3
Classifier: License :: OSI Approved :: Apache Software License
Classifier: Operating System :: OS Independent
Requires-Python: >=3.7
